vldt-0.1.2.dist-info/LICENSE
vldt-0.1.2.dist-info/WHEEL
vldt-0.1.2.dist-info/RECORD
vldt-0.1.2.dist-info/top_level.txt
vldt-0.1.2.dist-info/METADATA
tests/test_vldt.py
tests/test_deserialization.py
tests/conftest.py
tests/test_types.py
tests/test_async_validators.py
tests/test_fields.py
tests/test_docs.py
tests/__init__.py
tests/test_json.py
tests/test_validators.py
tests/test_dict.py
vldt.libs/libstdc++-0d31ccbe.so.6.0.32
vldt.libs/libgcc_s-a0b57c20.so.1
vldt/validators.py
vldt/models.py
vldt/fields.py
vldt/config.py
vldt/deserializer.py
vldt/models.pyi
vldt/__init__.py
vldt/_vldt.cpython-311-x86_64-linux-musl.so
