Metadata-Version: 2.2
Name: vldt
Version: 0.1.2
Summary: High-Performance Data Validation for Python
Author: Roman Right
Author-email: Roman Right <roman-right@protonmail.com>
Classifier: Programming Language :: Python :: 3
Classifier: Programming Language :: Python :: 3.11
Classifier: Programming Language :: Python :: 3.12
Classifier: Programming Language :: Python :: 3.13
Requires-Python: >=3.11
License-File: LICENSE
Requires-Dist: typing_extensions>=4.0.0
Provides-Extra: test
Requires-Dist: pre-commit>=3.5.0; extra == "test"
Requires-Dist: pytest>=8.3.3; extra == "test"
Requires-Dist: pytest-asyncio>=0.24.0; extra == "test"
Requires-Dist: pytest-cov>=5.0.0; extra == "test"
Dynamic: author
Dynamic: requires-python
